{"version":1,"resource":"file:///home/dark/University/Semester%205/Programming/Dcoms/Java/Addition_RFI/Server.java","entries":[{"id":"DK2R.java","timestamp":1663124542694},{"id":"z1Nd.java","timestamp":1663124702974},{"id":"EgOC.java","timestamp":1663124773737},{"id":"Qt6P.java","timestamp":1663126194967},{"id":"DOF3.java","timestamp":1663126266897},{"id":"Au0D.java","timestamp":1663126383554},{"id":"OWPO.java","timestamp":1663126413361},{"id":"Q8ub.java","timestamp":1663126425441},{"id":"c7xV.java","timestamp":1663126440611},{"id":"scip.java","source":"undoRedo.source","timestamp":1663126651367},{"id":"iOpP.java","timestamp":1663126684267}]}